drmaa2/__init__.py
drmaa2/byte_string.py
drmaa2/drmaa2_constants.py
drmaa2/drmaa2_ctypes.py
drmaa2/drmaa2_exceptions.py
drmaa2/drmaa2_job_list_descriptor.py
drmaa2/drmaa2_object.py
drmaa2/drmaa2_object_descriptors.py
drmaa2/drmaa2_slot_info_list_descriptor.py
drmaa2/drmaa2_version_descriptor.py
drmaa2/exception_mapper.py
drmaa2/job.py
drmaa2/job_array.py
drmaa2/job_info.py
drmaa2/job_session.py
drmaa2/job_template.py
drmaa2/library_manager.py
drmaa2/log_manager.py
drmaa2/machine_info.py
drmaa2/monitoring_session.py
drmaa2/notification.py
drmaa2/queue_info.py
drmaa2/reservation.py
drmaa2/reservation_info.py
drmaa2/reservation_session.py
drmaa2/reservation_template.py
drmaa2/singleton.py
drmaa2/slot_info.py
drmaa2/sudo.py
drmaa2/version.py
uge_drmaa2-8.11.0.dist-info/LICENSE
uge_drmaa2-8.11.0.dist-info/METADATA
uge_drmaa2-8.11.0.dist-info/WHEEL
uge_drmaa2-8.11.0.dist-info/top_level.txt
uge_drmaa2-8.11.0.dist-info/RECORD
