Metadata-Version: 2.1
Name: uge-drmaa2
Version: 8.11.0
Summary: UGE DRMAA2 Python API
Home-page: https://www.altair.com
Author: Altair Engineering Inc.
Author-email: support@altair.com
License: Apache 2.0
Platform: Posix; MacOS X
Classifier: Intended Audience :: Developers
Classifier: Operating System :: OS Independent
Classifier: Programming Language :: Python :: 2.7
Classifier: Programming Language :: Python :: 3
